uart.v
// clk is expected to be the full 100MHz clock
// 100_000_000 / 115_200 = 868.0556
module UART(input clk, input serialIn, output serialOut, input setAddr, input [11:0] startAddr, output err, output [11:0] writeAddr, output [31:0] writeData, output writeEnable);
    reg [11:0] timer = 12'b0;
    reg waitingForBit = 1'b1;
    reg [3:0] bitCounter = 1'd0;
    reg errored = 1'b0;
    assign err = errored;

    reg [1:0] currentByte = 2'b0;
    reg [31:0] data = 32'b0;
    assign writeData = data;
    reg [7:0] byte = 8'b0;
    reg writeOut = 1'b0;
    reg [11:0] addrOut = 12'b0;
    assign writeAddr = addrOut;

    assign writeEnable = writeOut;

    always @(posedge clk) begin
        if (setAddr) begin
            addrOut <= startAddr;
            currentByte <= 2'b0;
            data <= 32'b0;
        end
        if (writeOut) begin
            writeOut <= 1'b0;
            if (currentByte == 2'b0) begin
                addrOut <= addrOut + 1;
                data <= 32'b0;
            end
        end
        timer <= timer - 1;
        if (waitingForBit) begin
            // Falling edge of start bit
            if (!serialIn) begin
                // Wait 1.5 bits to end up in the middle of the first data bit
                timer <= 12'd1302;
                waitingForBit <= 1'b0;
                bitCounter <= 4'd0;
            end
        end else begin
            if (timer == 12'd0) begin
                timer <= 12'd868;
                bitCounter <= bitCounter + 1;
                // 9th bit is stop bit
                if (bitCounter == 4'd9) begin
                    waitingForBit <= 1'b1;
                    data[8*currentByte +: 8] <= byte;
                    // Write the current word to memory after each byte
                    writeOut = 1'b1;
                    currentByte <= currentByte + 1;
                    if (!serialIn) begin
                        errored <= 1'b1;
                    end
                end else begin
                    byte = {serialIn, byte[7:1]};
                end
            end
        end
    end
endmodule

uart_tb.v
module UART_tb();
    reg clk = 1'b0;
    reg serialIn = 1'b1;
    wire serialOut;
    reg setAddr = 1'b0;
    reg [11:0] startAddr = 12'b0;
    wire err;
    wire [11:0] writeAddr;
    wire [31:0] writeData;
    wire writeEnable;
    UART uut(clk, serialIn, serialOut, setAddr, startAddr, err, writeAddr, writeData, writeEnable);
    initial begin
        $dumpfile("uart.vcd");
        $dumpvars(0, UART_tb);
        clk = 1'b0;
        #10;
        clk = 1'b1;
        #10;
        clk = 1'b0;
        serialIn <= 1'b1;
        #10;
        clk = 1'b1;
        #10;
        clk = 1'b0;
        #10;
        clk = 1'b1;
        #10;
        clk = 1'b0;
        serialIn <= 1'b0;
        #10;
        clk = 1'b1;
        #10;
        clk = 1'b0;
        serialIn <= 1'b0;
        #10;
        clk = 1'b1;
        #10;
        clk = 1'b0;
        serialIn <= 1'b1;
        #10;
        clk = 1'b1;
        #10;
        clk = 1'b0;
        serialIn <= 1'b1;
        #10;
        clk = 1'b1;
        #10;
        clk = 1'b0;
        serialIn <= 1'b0;
        #10;
        clk = 1'b1;
        #10;
        clk = 1'b0;
        serialIn <= 1'b1;
        #10;
        clk = 1'b1;
        #10;
        clk = 1'b0;
        #10;
        clk = 1'b1;
        #10;
        clk = 1'b0;
        serialIn <= 1'b0;
        #10;
        clk = 1'b1;
        #10;
        clk = 1'b0;
        serialIn <= 1'b1;
        #10;
        clk = 1'b1;
        #10;
        clk = 1'b0;
        #10;
        clk = 1'b1;
        #10;
        clk = 1'b0;
        #10;
        clk = 1'b1;
        #10;
        clk = 1'b0;
        serialIn <= 1'b0;
        #10;
        clk = 1'b1;
        #10;
        clk = 1'b0;
        #10;
        clk = 1'b1;
        #10;
        clk = 1'b0;
        #10;
        clk = 1'b1;
        #10;
        clk = 1'b0;
        #10;
        clk = 1'b1;
        #10;
        clk = 1'b0;
        serialIn <= 1'b1;
        #10;
        clk = 1'b1;
        #10;
        clk = 1'b0;
        #10;
        clk = 1'b1;
        #10;
        clk = 1'b0;
        #10;
        clk = 1'b1;
        #10;
        clk = 1'b0;
        #10;
        clk = 1'b1;
        #10;
        clk = 1'b0;
        #10;
        clk = 1'b1;
        #10;
        clk = 1'b0;
        #10;
        clk = 1'b1;
        #10;
        clk = 1'b0;
        #10;
        clk = 1'b1;
        #10;
        $finish;
    end
endmodule

uart.vcd
$date
	Tue Apr 18 12:59:43 2023
$end
$version
	Icarus Verilog
$end
$timescale
	1s
$end
$scope module UART_tb $end
$var wire 1 ! serialOut $end
$var wire 1 " writeEnable $end
$var wire 32 # writeData [31:0] $end
$var wire 12 $ writeAddr [11:0] $end
$var wire 1 % err $end
$var reg 1 & clk $end
$var reg 1 ' serialIn $end
$var reg 1 ( setAddr $end
$var reg 12 ) startAddr [11:0] $end
$scope module uut $end
$var wire 1 & clk $end
$var wire 1 % err $end
$var wire 1 ' serialIn $end
$var wire 1 ! serialOut $end
$var wire 1 ( setAddr $end
$var wire 12 * startAddr [11:0] $end
$var wire 12 + writeAddr [11:0] $end
$var wire 32 , writeData [31:0] $end
$var wire 1 " writeEnable $end
$var reg 12 - addrOut [11:0] $end
$var reg 4 . bitCounter [3:0] $end
$var reg 8 / byte [7:0] $end
$var reg 2 0 currentByte [1:0] $end
$var reg 32 1 data [31:0] $end
$var reg 1 2 errored $end
$var reg 12 3 timer [11:0] $end
$var reg 1 4 waitingForBit $end
$var reg 1 5 writeOut $end
$upscope $end
$upscope $end
$enddefinitions $end
$comment Show the parameter values. $end
$dumpall
$end
#0
$dumpvars
05
14
b0 3
02
b0 1
b0 0
b0 /
b0 .
b0 -
b0 ,
b0 +
b0 *
b0 )
0(
1'
0&
0%
b0 $
b0 #
0"
z!
$end
#10
b111111111111 3
1&
#20
0&
#30
b111111111110 3
1&
#40
0&
#50
b111111111101 3
1&
#60
0'
0&
#70
04
b1 3
1&
#80
0&
#90
b0 3
1&
#100
1'
0&
#110
b1 .
b1 3
b10000000 /
1&
#120
0&
#130
b0 3
1&
#140
0'
0&
#150
b10 .
b1 3
b1000000 /
1&
#160
1'
0&
#170
b0 3
1&
#180
0&
#190
b11 .
b1 3
b10100000 /
1&
#200
0'
0&
#210
b0 3
1&
#220
1'
0&
#230
b100 .
b1 3
b11010000 /
1&
#240
0&
#250
b0 3
1&
#260
0&
#270
b101 .
b1 3
b11101000 /
1&
#280
0'
0&
#290
b0 3
1&
#300
0&
#310
b110 .
b1 3
b1110100 /
1&
#320
0&
#330
b0 3
1&
#340
0&
#350
b111 .
b1 3
b111010 /
1&
#360
1'
0&
#370
b0 3
1&
#380
0&
#390
b1000 .
b1 3
b10011101 /
1&
#400
0&
#410
b0 3
1&
#420
0&
#430
b1001 .
b1 3
b11001110 /
1&
#440
0&
#450
b0 3
1&
#460
0&
#470
b1 0
b11001110 #
b11001110 ,
b11001110 1
14
b1010 .
b1 3
1"
15
1&
#480
0&
#490
b0 3
0"
05
1&
